{
  "version": "1.0",
  "note": "戸建て80㎡フルリノベーション（スケルトン型）標準BOM。建設実務30年・大賀俊勝監修。JCCDB v1.2準拠。",
  "sqm": 80,
  "tsubo": 24.2,
  "categories": {
    "解体・仮設": [
      {
        "name": "養生シート（ブルーシート #3000）",
        "unit": "枚",
        "qty": 20,
        "unit_price": 800,
        "memo": "開口部・搬出路養生"
      },
      {
        "name": "養生テープ（50mm×25m）",
        "unit": "巻",
        "qty": 30,
        "unit_price": 180,
        "memo": "養生固定"
      },
      {
        "name": "解体袋（土嚢袋）",
        "unit": "枚",
        "qty": 200,
        "unit_price": 25,
        "memo": "小物廃材収集"
      },
      {
        "name": "仮設トイレリース（2ヶ月）",
        "unit": "台",
        "qty": 1,
        "unit_price": 20000,
        "memo": "月1万×2ヶ月"
      },
      {
        "name": "仮設電力（工事用分電盤）",
        "unit": "式",
        "qty": 1,
        "unit_price": 30000,
        "memo": "2ヶ月分"
      }
    ],
    "木構造材（補修・追加）": [
      {
        "name": "KD材 105×105×3000mm（杉・乾燥）",
        "unit": "本",
        "qty": 8,
        "unit_price": 3200,
        "memo": "間柱補修・追加。腐食柱交換用"
      },
      {
        "name": "KD材 45×105×3000mm（杉・間柱）",
        "unit": "本",
        "qty": 20,
        "unit_price": 1200,
        "memo": "間柱追加"
      },
      {
        "name": "KD材 45×45×3000mm（胴縁）",
        "unit": "本",
        "qty": 40,
        "unit_price": 600,
        "memo": "外壁下地胴縁"
      },
      {
        "name": "KD材 30×40×3000mm（野縁）",
        "unit": "本",
        "qty": 60,
        "unit_price": 400,
        "memo": "天井下地野縁"
      },
      {
        "name": "LVL梁 105×210×4000mm",
        "unit": "本",
        "qty": 4,
        "unit_price": 8500,
        "memo": "開口補強梁"
      },
      {
        "name": "土台ヒノキ 105×105×3000mm",
        "unit": "本",
        "qty": 4,
        "unit_price": 5500,
        "memo": "腐食土台部分交換"
      }
    ],
    "構造用合板・面材": [
      {
        "name": "構造用合板 9mm 910×1820mm",
        "unit": "枚",
        "qty": 30,
        "unit_price": 1800,
        "memo": "壁・床下地"
      },
      {
        "name": "構造用合板 12mm 910×1820mm",
        "unit": "枚",
        "qty": 20,
        "unit_price": 2200,
        "memo": "床下地・耐力壁"
      },
      {
        "name": "構造用合板 24mm 910×1820mm",
        "unit": "枚",
        "qty": 15,
        "unit_price": 4500,
        "memo": "床根太レス工法"
      },
      {
        "name": "OSB合板 9mm 910×1820mm",
        "unit": "枚",
        "qty": 10,
        "unit_price": 1600,
        "memo": "外壁下地代替"
      }
    ],
    "釘・ビス・金物": [
      {
        "name": "コーススレッド 3.8×65mm（500本箱）",
        "unit": "箱",
        "qty": 6,
        "unit_price": 1100,
        "memo": "木下地全般固定"
      },
      {
        "name": "コーススレッド 3.8×90mm（500本箱）",
        "unit": "箱",
        "qty": 4,
        "unit_price": 1400,
        "memo": "構造木材固定"
      },
      {
        "name": "ビス 3.5×32mm（500本箱）",
        "unit": "箱",
        "qty": 4,
        "unit_price": 680,
        "memo": "内装薄物固定"
      },
      {
        "name": "フロアビス 3.8×45mm（200本箱）",
        "unit": "箱",
        "qty": 6,
        "unit_price": 720,
        "memo": "フローリング固定専用"
      },
      {
        "name": "N釘 N65（1kg）",
        "unit": "kg",
        "qty": 8,
        "unit_price": 320,
        "memo": "間柱・下地固定。1kg≒280本"
      },
      {
        "name": "N釘 N75（1kg）",
        "unit": "kg",
        "qty": 5,
        "unit_price": 340,
        "memo": "構造材固定"
      },
      {
        "name": "CN釘 CN90（1kg）",
        "unit": "kg",
        "qty": 6,
        "unit_price": 480,
        "memo": "構造用合板固定必須"
      },
      {
        "name": "GNF ボードビス 25mm（1000本）",
        "unit": "箱",
        "qty": 8,
        "unit_price": 850,
        "memo": "石膏ボード固定専用。1枚≒20本"
      },
      {
        "name": "ステンレスビス 3.5×45mm（100本）",
        "unit": "箱",
        "qty": 3,
        "unit_price": 1400,
        "memo": "水回り・外部用"
      },
      {
        "name": "プラグ 6mm（100個袋）",
        "unit": "袋",
        "qty": 5,
        "unit_price": 280,
        "memo": "コンクリートへの固定"
      },
      {
        "name": "ケミカルアンカー M10×130mm",
        "unit": "本",
        "qty": 20,
        "unit_price": 220,
        "memo": "土台アンカー補修"
      }
    ],
    "断熱材": [
      {
        "name": "グラスウール 16K 50mm（1坪袋）",
        "unit": "袋",
        "qty": 15,
        "unit_price": 1800,
        "memo": "壁内断熱。1袋=1坪分"
      },
      {
        "name": "グラスウール 16K 100mm（1坪袋）",
        "unit": "袋",
        "qty": 15,
        "unit_price": 3200,
        "memo": "壁内断熱・高性能仕様"
      },
      {
        "name": "グラスウール 32K 50mm（1坪袋）",
        "unit": "袋",
        "qty": 10,
        "unit_price": 3800,
        "memo": "高性能グラスウール"
      },
      {
        "name": "発泡スチロール 50mm 910×1820mm",
        "unit": "枚",
        "qty": 25,
        "unit_price": 1200,
        "memo": "床下断熱（シロアリに強い）"
      },
      {
        "name": "発泡スチロール 100mm 910×1820mm",
        "unit": "枚",
        "qty": 15,
        "unit_price": 2200,
        "memo": "床下高断熱仕様"
      },
      {
        "name": "防湿シート 0.2mm×2m×50m",
        "unit": "巻",
        "qty": 3,
        "unit_price": 3500,
        "memo": "床下防湿。80㎡で約1.5巻"
      },
      {
        "name": "透湿防水シート 1m×50m",
        "unit": "巻",
        "qty": 4,
        "unit_price": 4200,
        "memo": "外壁下地防水層"
      }
    ],
    "内装下地材": [
      {
        "name": "石膏ボード 9.5mm 910×1820mm",
        "unit": "枚",
        "qty": 60,
        "unit_price": 700,
        "memo": "天井下地。80㎡天井で約50枚+ロス"
      },
      {
        "name": "石膏ボード 12.5mm 910×1820mm",
        "unit": "枚",
        "qty": 120,
        "unit_price": 850,
        "memo": "壁下地メイン。80㎡壁面で約100枚+ロス"
      },
      {
        "name": "強化石膏ボード 15mm 910×1820mm",
        "unit": "枚",
        "qty": 20,
        "unit_price": 1400,
        "memo": "水回り・準耐火部位"
      },
      {
        "name": "耐水石膏ボード 12.5mm 910×1820mm",
        "unit": "枚",
        "qty": 15,
        "unit_price": 1100,
        "memo": "浴室周辺・洗面所"
      },
      {
        "name": "ケイカル板 6mm 910×1820mm",
        "unit": "枚",
        "qty": 10,
        "unit_price": 1800,
        "memo": "水回り・防火部位"
      }
    ],
    "フローリング": [
      {
        "name": "複合フローリング 12mm 303×1818mm（1坪）",
        "unit": "坪",
        "qty": 27,
        "unit_price": 8000,
        "memo": "80㎡×1.1ロス=88㎡=26.7坪。2,400〜4,000円/㎡相当"
      },
      {
        "name": "フローリング接着剤 1kg缶",
        "unit": "缶",
        "qty": 15,
        "unit_price": 1200,
        "memo": "接着工法。5〜6㎡/缶"
      },
      {
        "name": "床下地合板 12mm（1坪）",
        "unit": "坪",
        "qty": 27,
        "unit_price": 2500,
        "memo": "フローリング下地"
      },
      {
        "name": "根太 45×45×3000mm",
        "unit": "本",
        "qty": 30,
        "unit_price": 600,
        "memo": "床組み補修・追加"
      },
      {
        "name": "大引 90×90×3000mm",
        "unit": "本",
        "qty": 10,
        "unit_price": 2200,
        "memo": "床組み補修"
      },
      {
        "name": "束（プラ束 高さ調整式）",
        "unit": "個",
        "qty": 40,
        "unit_price": 350,
        "memo": "床下支持"
      }
    ],
    "クロス・内装仕上げ": [
      {
        "name": "一般クロス（量産品 92cm×50m）",
        "unit": "巻",
        "qty": 8,
        "unit_price": 3500,
        "memo": "壁+天井合計280㎡。1巻=46㎡×1.15ロス"
      },
      {
        "name": "クロス糊（でんぷん糊 20kg）",
        "unit": "袋",
        "qty": 3,
        "unit_price": 2800,
        "memo": "1袋≒100㎡分"
      },
      {
        "name": "クロス下地処理剤（シーラー 16L）",
        "unit": "缶",
        "qty": 3,
        "unit_price": 4500,
        "memo": "旧クロス撤去後の下地処理"
      },
      {
        "name": "パテ（クロス下地 20kg）",
        "unit": "袋",
        "qty": 5,
        "unit_price": 1800,
        "memo": "ボード目地・段差処理"
      },
      {
        "name": "コーナーテープ（25mm×25m）",
        "unit": "巻",
        "qty": 5,
        "unit_price": 380,
        "memo": "出隅補強"
      }
    ],
    "給排水配管材": [
      {
        "name": "架橋ポリエチレン管 13mm（50m巻）",
        "unit": "巻",
        "qty": 3,
        "unit_price": 8500,
        "memo": "給水配管。80㎡全更新で約150m"
      },
      {
        "name": "架橋ポリエチレン管 20mm（30m巻）",
        "unit": "巻",
        "qty": 2,
        "unit_price": 7200,
        "memo": "給湯幹線"
      },
      {
        "name": "塩ビ管 VP100（4m）",
        "unit": "本",
        "qty": 8,
        "unit_price": 2800,
        "memo": "排水横管 100径"
      },
      {
        "name": "塩ビ管 VP75（4m）",
        "unit": "本",
        "qty": 6,
        "unit_price": 2200,
        "memo": "排水横管 75径"
      },
      {
        "name": "塩ビ管 VP50（4m）",
        "unit": "本",
        "qty": 10,
        "unit_price": 1600,
        "memo": "排水枝管 50径"
      },
      {
        "name": "排水継手 VP100エルボ",
        "unit": "個",
        "qty": 15,
        "unit_price": 680,
        "memo": "排水曲がり部"
      },
      {
        "name": "排水継手 VP100チーズ",
        "unit": "個",
        "qty": 8,
        "unit_price": 920,
        "memo": "排水分岐"
      },
      {
        "name": "止水栓 13mm（アングル型）",
        "unit": "個",
        "qty": 8,
        "unit_price": 1200,
        "memo": "各設備接続部"
      },
      {
        "name": "フレキ管 13mm×300mm",
        "unit": "本",
        "qty": 10,
        "unit_price": 850,
        "memo": "水栓接続用"
      }
    ],
    "電気配線材": [
      {
        "name": "VVFケーブル 2.0mm×2芯（100m巻）",
        "unit": "巻",
        "qty": 4,
        "unit_price": 12000,
        "memo": "一般回路配線。80㎡全更新で約400m"
      },
      {
        "name": "VVFケーブル 2.0mm×3芯（100m巻）",
        "unit": "巻",
        "qty": 1,
        "unit_price": 18000,
        "memo": "エアコン専用回路"
      },
      {
        "name": "VVFケーブル 2.6mm×2芯（100m巻）",
        "unit": "巻",
        "qty": 2,
        "unit_price": 22000,
        "memo": "IH・電気温水器幹線"
      },
      {
        "name": "コンセントプレート（1口 ホワイト）",
        "unit": "個",
        "qty": 30,
        "unit_price": 280,
        "memo": "80㎡標準で25〜35個"
      },
      {
        "name": "スイッチ（片切 ホワイト）",
        "unit": "個",
        "qty": 20,
        "unit_price": 350,
        "memo": "照明スイッチ"
      },
      {
        "name": "引掛シーリング（直付け）",
        "unit": "個",
        "qty": 15,
        "unit_price": 480,
        "memo": "照明取付金具"
      },
      {
        "name": "分電盤（主幹40A 14回路）",
        "unit": "台",
        "qty": 1,
        "unit_price": 18000,
        "memo": "全更新。IH対応"
      },
      {
        "name": "電線管（PF管 16mm 50m巻）",
        "unit": "巻",
        "qty": 3,
        "unit_price": 2800,
        "memo": "露出配管・保護"
      }
    ],
    "塗装・コーキング": [
      {
        "name": "変性シリコン コーキング（320ml）",
        "unit": "本",
        "qty": 20,
        "unit_price": 480,
        "memo": "内外部目地。1本=約4〜6m"
      },
      {
        "name": "ウレタンコーキング（320ml）",
        "unit": "本",
        "qty": 10,
        "unit_price": 420,
        "memo": "可動部位・外部"
      },
      {
        "name": "水性塗料 外部用（16L）",
        "unit": "缶",
        "qty": 3,
        "unit_price": 8500,
        "memo": "庇・軒天塗装"
      },
      {
        "name": "水性塗料 内部用（14L）",
        "unit": "缶",
        "qty": 2,
        "unit_price": 6500,
        "memo": "天井・壁塗装部位"
      },
      {
        "name": "プライマー（下塗り 16L）",
        "unit": "缶",
        "qty": 2,
        "unit_price": 4500,
        "memo": "塗装下地処理"
      }
    ],
    "産廃・廃材処理": [
      {
        "name": "木くず処分費（1m³）",
        "unit": "m³",
        "qty": 15,
        "unit_price": 6500,
        "memo": "柱・梁・建具・フローリング"
      },
      {
        "name": "石膏ボード処分費（1m³）",
        "unit": "m³",
        "qty": 8,
        "unit_price": 10000,
        "memo": "旧壁材・天井材"
      },
      {
        "name": "混合廃棄物処分費（1m³）",
        "unit": "m³",
        "qty": 5,
        "unit_price": 22000,
        "memo": "分別不可能な混合物"
      },
      {
        "name": "廃プラ・断熱材処分費（1m³）",
        "unit": "m³",
        "qty": 3,
        "unit_price": 15000,
        "memo": "旧断熱材・配管被覆"
      },
      {
        "name": "金属くず（1トン）",
        "unit": "t",
        "qty": 0.5,
        "unit_price": -8000,
        "memo": "マイナス=売却益。銅管・鉄骨"
      }
    ]
  },
  "categories_total": {
    "解体・仮設": 76400,
    "木構造材（補修・追加）": 153600,
    "構造用合板・面材": 181500,
    "釘・ビス・金物": 43180,
    "断熱材": 203300,
    "内装下地材": 206500,
    "フローリング": 355500,
    "クロス・内装仕上げ": 60800,
    "給排水配管材": 127160,
    "電気配線材": 159000,
    "塗装・コーキング": 61300,
    "産廃・廃材処理": 328500.0
  },
  "total_material_cost": 1956740.0,
  "note_material_only": "材料費のみ。工賃・諸経費別途"
}