{
  "_meta": {
    "version": "1.0-toshi-philosophy",
    "updated": "2026-04-25",
    "category_id": "uchimado_nijusashi_work",
    "category_name_jp": "内窓・二重サッシ（二重窓）設置リフォーム",
    "maintainer": "TOshi (大賀 俊勝) / HORIZON SHIELD",
    "importance": "⭐⭐⭐⭐⭐ 先進的窓リノベ2026補助金（上限100万円）が強烈・1箇所30分〜1時間で完工・省エネ補助金の中で最もコスパが高いカテゴリ",
    "knowledge_source": "環境省「先進的窓リノベ2026事業」公式サイト（2026年4月24日確認）/ リフォームガイド 2026年最新版 / リショップナビ 窓リフォーム補助金2026 / LIXIL インプラス・リプラス 2026年カタログ / YKKap プラマードU・ウチリモ / 二重サッシ費用手引き 各種施工事例 / 国土交通省 みらいエコ住宅2026事業 / 国交省 長期優良住宅化リフォーム推進事業",
    "scope": "既存住宅の内側への内窓（二重窓・二重サッシ）設置・交換。外窓交換（カバー工法・はつり工法）・ガラス交換も含む",
    "horizons_philosophy": "内窓設置は2026年の省エネリフォームで最もコスパが高い工事。1箇所30分〜1時間で完工し、先進的窓リノベ2026補助金で最大100万円が補助される。断熱・防音・結露防止の三役をこなす。ただし補助金は予算上限到達次第終了（先着順）のため、申請は急ぐべき。window_reform.jsonとは補助金体系が独立しているため別ファイルで管理。"
  },
  "horizon_shield_standard": {
    "description": "HS基準：健全な業者が施主に請求すべき金額の算出ルール（内窓版）",
    "formula": "内窓本体価格 × 1.15 + 施工費（1箇所3〜7万円） + ふかし枠等オプション費 + (原価 × 一般管理費率 15%) + 消費税 10%",
    "parameters": {
      "product_markup": 1.15,
      "general_overhead_pct_ideal": 15,
      "tax_pct": 10
    },
    "philosophy": "内窓は製品定価の60〜70%が業者仕入れ値。複数窓を同時設置すると施工単価が下がる。補助金申請サポートができる業者（住宅省エネ支援事業者登録済み）を選ぶことが最重要。"
  },
  "window_reform_methods": {
    "inner_window_new": {
      "name": "内窓設置（最も一般的・補助金対象）",
      "description": "既存の外窓はそのまま残し、室内側に新たに内窓を設置して二重窓化",
      "work_time_per_window": "30分〜1時間",
      "merit": [
        "既存窓を壊さない・工事が最短",
        "断熱・防音・防犯・結露防止の四役",
        "先進的窓リノベ2026で最大補助を受けやすい",
        "マンションでも可能（管理規約要確認）",
        "工期中の生活への影響が最小"
      ],
      "demerit": [
        "窓が2枚になるため開け閉めが二度手間",
        "窓枠の奥行きが足りない場合はふかし枠（オプション）が必要",
        "出窓への設置は補助対象外になることがある"
      ],
      "HS_recommendation": "⭐⭐⭐⭐⭐ 第一推奨。補助金+効果+工期の三拍子が揃う"
    },
    "outer_window_cover": {
      "name": "外窓交換（カバー工法）",
      "description": "既存の窓枠を残したまま、上からカバーして新しい外窓を設置",
      "work_time_per_window": "1〜2時間",
      "merit": [
        "壁を壊さずに外窓を交換できる",
        "先進的窓リノベ2026の補助対象",
        "内窓より開閉が1回で済む"
      ],
      "demerit": [
        "既存窓枠を覆うため窓が少し小さくなる",
        "内窓設置より費用が高い",
        "樹脂・アルミ樹脂複合サッシが必要（補助金条件）"
      ]
    },
    "outer_window_hatsuri": {
      "name": "外窓交換（はつり工法）",
      "description": "既存窓枠を撤去し、壁を壊して新しい窓枠ごと交換",
      "merit": ["窓サイズを変更できる", "最も高い断熱性能を実現できる"],
      "demerit": [
        "壁の解体・修復が必要で工期が長い",
        "費用が最も高い",
        "カバー工法より補助金額が少ない場合あり"
      ]
    },
    "glass_only_exchange": {
      "name": "ガラス交換のみ",
      "description": "既存サッシはそのまま、ガラスだけを複層ガラス・Low-Eガラスに交換",
      "merit": ["費用が安い"],
      "demerit": [
        "サッシ・窓枠からの熱損失は改善しない",
        "ガラス部の結露は減るがサッシには結露が残る",
        "補助金対象の要件が厳しく実質的に対象外になりやすい"
      ],
      "HS_note": "コスト優先の場合のみ選択。断熱効果は内窓設置より大幅に劣る"
    }
  },
  "subsidy_2026": {
    "senshin_mado_renobe_2026": {
      "name": "先進的窓リノベ2026事業（環境省）",
      "operator": "環境省",
      "target_work": ["内窓設置", "外窓交換（カバー工法）", "外窓交換（はつり工法）", "ガラス交換"],
      "max_subsidy_detached": 1000000,
      "max_subsidy_apartment": 1000000,
      "contract_period": "2025年12月〜2026年12月（予算上限到達次第終了）",
      "grade_system": {
        "SS_grade": "最高断熱性能（最大補助額）",
        "S_grade": "高断熱性能",
        "note": "Uw値（熱貫流率）で決定。値が低いほど高グレード"
      },
      "mansion_examples_S_grade": {
        "特大_4平米以上": 83000,
        "大": 57000,
        "中": 37000,
        "小": 24000
      },
      "house_example": "15箇所設置で50〜60万円程度の補助",
      "procedure": [
        "住宅省エネ支援事業者登録済み業者を選ぶ（必須）",
        "業者を通じて交付申請予約（着工前に必要）",
        "工事完了後に業者が申請書類作成をサポート",
        "事務局審査後に補助金振込（施主への直接交付）"
      ],
      "HS_warning": "⚠️ 予算上限到達次第終了（先着順）。2026年4月24日時点で申請進行中。早期申請が必須",
      "important_note": "補助金申請は住宅省エネ支援事業者登録済みの業者でないと手続きができない。登録業者かどうかを必ず確認"
    },
    "mirai_eco_2026": {
      "name": "みらいエコ住宅2026事業（国土交通省・環境省）",
      "operator": "国土交通省・環境省",
      "target_work": "窓単独での申請は不可。断熱改修と省エネ設備の組み合わせが必要",
      "max_subsidy": 1000000,
      "note": "先進的窓リノベと連携申請が可能。窓リノベ側で窓工事要件を満たせば、みらいエコ側でバリアフリー等の別工事を申請できる",
      "combination": "insulation_work.json・kaidan_reform.json等との同時申請で最大効果"
    },
    "dansetu_reform_shien": {
      "name": "既存住宅における断熱リフォーム支援事業（環境省）",
      "max_subsidy_detached": 1200000,
      "max_subsidy_apartment": 150000,
      "subsidy_rate": "費用の1/3以内",
      "types": ["トータル断熱（住宅全体の断熱性能向上）", "居間だけ断熱（居間の全窓断熱）"]
    },
    "choki_yuryo": {
      "name": "長期優良住宅化リフォーム推進事業（国土交通省）",
      "max_subsidy": 800000,
      "subsidy_rate": "インスペクション費用＋工事費の1/3",
      "note": "断熱性向上（省エネ）として申請。insulation_work.jsonと連携"
    },
    "key_advice": "まず先進的窓リノベ2026（最も使いやすい）で申請。予算終了後はみらいエコ住宅2026または断熱リフォーム支援事業を検討"
  },
  "product_grades_and_makers": {
    "SS_grade": {
      "description": "最高断熱性能（Low-E複層ガラス＋樹脂フレーム）",
      "makers": ["LIXIL インプラス（Low-E複層）", "YKKap プラマードU（Low-E複層）"],
      "subsidy_merit": "最大補助額を受けやすい"
    },
    "S_grade": {
      "description": "高断熱性能（複層ガラス＋樹脂フレーム）",
      "makers": ["LIXIL インプラス", "YKKap プラマードU・ウチリモ", "三協アルミ 内窓プラスト"],
      "subsidy_merit": "補助金対象・コスパ良い"
    },
    "window_types_by_shape": {
      "hikichigai": "引き違い窓（最多）",
      "fix": "FIX窓（はめ殺し）",
      "tate_suberi": "縦すべり出し窓",
      "yoko_suberi": "横すべり出し窓",
      "tenjo_mado": "天窓（コストが特に高い）"
    },
    "frame_depth_caution": "窓枠の奥行きが50mm未満の場合はふかし枠が必要（マンションや古い住宅で多い）。ふかし枠1箇所で1〜3万円追加"
  },
  "standard_work_items_jpy": {
    "inner_window_small_per_unit": {
      "min": 30000, "max": 60000,
      "note": "内窓 小（腰高窓・W900×H900mm以下）1箇所・材工込み"
    },
    "inner_window_medium_per_unit": {
      "min": 50000, "max": 90000,
      "note": "内窓 中（腰高窓・W1500×H1000mm程度）1箇所・材工込み"
    },
    "inner_window_large_per_unit": {
      "min": 80000, "max": 150000,
      "note": "内窓 大（掃き出し窓・W1800×H2000mm程度）1箇所・材工込み"
    },
    "inner_window_extra_large_per_unit": {
      "min": 120000, "max": 200000,
      "note": "内窓 特大（W2000×H2000mm以上）1箇所・材工込み"
    },
    "fukashi_frame_per_unit": {
      "min": 10000, "max": 30000,
      "note": "ふかし枠（窓枠奥行き不足時のオプション）1箇所あたり"
    },
    "outer_window_cover_medium": {
      "min": 80000, "max": 150000,
      "note": "外窓交換 カバー工法 中サイズ 1箇所・材工込み"
    },
    "outer_window_hatsuri_medium": {
      "min": 150000, "max": 300000,
      "note": "外窓交換 はつり工法 中サイズ 1箇所・材工込み（壁修復込み）"
    },
    "glass_exchange_per_unit": {
      "min": 30000, "max": 80000,
      "note": "ガラス交換のみ（Low-E複層ガラス・既存サッシ利用）1枚あたり"
    }
  },
  "plans": {
    "inner_window_3rooms": {
      "name": "内窓設置 3部屋（リビング1＋寝室2・6箇所）戸建て",
      "scope": "中〜大サイズ内窓6箇所・材工込み・補助金申請サポート",
      "window_count": 6,
      "estimated_total_jpy": { "min": 300000, "max": 600000 },
      "subsidy_estimate_jpy": { "min": 150000, "max": 350000 },
      "net_cost_after_subsidy": { "min": 100000, "max": 400000 },
      "hs_rule_estimate_jpy": 420000,
      "work_days": 1,
      "work_hours": "3〜6時間",
      "subsidy_note": "先進的窓リノベ2026でSグレード申請時の目安補助額",
      "料金_業者規模別_税込_円": {
        "区分1_個人サッシ職人": { "min": 250000, "max": 370000 },
        "区分2_中小窓専門店": { "min": 370000, "max": 480000 },
        "区分3_人気リフォーム会社": { "min": 490000, "max": 590000 },
        "区分4_大手リフォーム_HM系": { "min": 610000, "max": 780000 }
      },
      "_価格基準": "TOshi Rule原価ベース + 業者規模別妥当利益率レンジ"
    },
    "inner_window_full_house": {
      "name": "内窓設置 全室（戸建て3LDK・10〜15箇所）補助金フル活用",
      "scope": "全居室・水回り以外の全窓に内窓設置。先進的窓リノベ2026申請込み",
      "window_count": 12,
      "estimated_total_jpy": { "min": 600000, "max": 1500000 },
      "subsidy_estimate_jpy": { "min": 400000, "max": 800000 },
      "net_cost_after_subsidy": { "min": 200000, "max": 900000 },
      "hs_rule_estimate_jpy": 950000,
      "work_days": 1,
      "work_hours": "6〜10時間（複数職人で1日完工可能）",
      "subsidy_note": "SSグレード全窓で60〜80万円補助の可能性あり",
      "HS_note": "補助金が最大化されるプラン。一番コスパが高い。窓の多い戸建てで特に有利",
      "料金_業者規模別_税込_円": {
        "区分1_個人サッシ職人": { "min": 500000, "max": 800000 },
        "区分2_中小窓専門店": { "min": 800000, "max": 1100000 },
        "区分3_人気リフォーム会社": { "min": 1100000, "max": 1400000 },
        "区分4_大手リフォーム_HM系": { "min": 1400000, "max": 1800000 }
      },
      "_価格基準": "TOshi Rule原価ベース + 業者規模別妥当利益率レンジ"
    },
    "inner_window_mansion_4rooms": {
      "name": "内窓設置 マンション 3LDK（4〜6箇所）",
      "scope": "マンション居室窓4〜6箇所に内窓設置。管理規約確認込み",
      "window_count": 5,
      "estimated_total_jpy": { "min": 200000, "max": 450000 },
      "subsidy_estimate_jpy": { "min": 120000, "max": 290000 },
      "net_cost_after_subsidy": { "min": 80000, "max": 280000 },
      "hs_rule_estimate_jpy": 300000,
      "work_days": 1,
      "mansion_notes": [
        "管理規約・管理組合への事前確認が必要",
        "外窓は共用部のため交換不可（内窓のみ可能が多い）",
        "窓枠奥行きが50mm未満の場合はふかし枠が必要"
      ],
      "料金_業者規模別_税込_円": {
        "区分1_個人サッシ職人": { "min": 170000, "max": 260000 },
        "区分2_中小窓専門店": { "min": 260000, "max": 350000 },
        "区分3_人気リフォーム会社": { "min": 360000, "max": 440000 },
        "区分4_大手リフォーム_HM系": { "min": 460000, "max": 590000 }
      },
      "_価格基準": "TOshi Rule原価ベース + 業者規模別妥当利益率レンジ"
    },
    "single_window_soundproof": {
      "name": "内窓1箇所（防音重視・道路沿い・線路沿い）",
      "scope": "防音効果の高い内窓（防音合わせガラス対応）1箇所設置",
      "window_count": 1,
      "estimated_total_jpy": { "min": 60000, "max": 150000 },
      "hs_rule_estimate_jpy": 95000,
      "work_days": 1,
      "work_hours": "1〜2時間",
      "note": "防音ガラス（ラミシャット等）を選択すると材料費が高くなるが防音効果が大幅UP",
      "料金_業者規模別_税込_円": {
        "区分1_個人サッシ職人": { "min": 50000, "max": 90000 },
        "区分2_中小窓専門店": { "min": 85000, "max": 120000 },
        "区分3_人気リフォーム会社": { "min": 120000, "max": 155000 },
        "区分4_大手リフォーム_HM系": { "min": 160000, "max": 220000 }
      },
      "_価格基準": "TOshi Rule原価ベース + 業者規模別妥当利益率レンジ"
    }
  },
  "red_flags": [
    {
      "code": "NOT_REGISTERED_SAVER",
      "pattern": "補助金申請ができると言いながら住宅省エネ支援事業者に未登録",
      "severity": "🔴 CRITICAL",
      "reason": "先進的窓リノベ2026の申請には、業者が「住宅省エネ支援事業者」として事前登録していることが必須。未登録業者では補助金申請ができない",
      "対処": "環境省・先進的窓リノベ2026公式サイトで業者の登録状況を確認してから契約"
    },
    {
      "code": "SUBSIDY_GUARANTEE_FALSE",
      "pattern": "補助金を必ず受け取れると断言する業者",
      "severity": "🚨 HIGH",
      "reason": "先進的窓リノベ2026は予算上限到達次第終了（先着順）。審査で却下されることもある。受領を保証できる業者は存在しない",
      "対処": "「補助金申請をサポートします」は正しい表現。「必ずもらえる」は誇大広告"
    },
    {
      "code": "BUDGET_EXHAUSTION_RISK_IGNORED",
      "pattern": "補助金の予算上限・終了リスクを説明しない",
      "severity": "🚨 HIGH",
      "reason": "先進的窓リノベは毎年予算が尽きると申請受付終了。2026年4月時点で申請が進行中のため、残予算を確認した上で急ぐかどうかを判断する必要がある",
      "対処": "環境省公式サイトで申請額の推移を確認してから착工・申請のタイミングを決める"
    },
    {
      "code": "WINDOW_GRADE_DOWNGRADE",
      "pattern": "補助金対象外のグレードの窓を提案してS/SS申請と言う",
      "severity": "🔴 CRITICAL",
      "reason": "補助金はUw値（熱貫流率）でグレード判定。基準を満たさない製品では補助金を受けられない",
      "対処": "メーカーが発行する性能証明書のUw値を確認。補助金対象グレードの製品か確認"
    },
    {
      "code": "FUKASHI_FRAME_NOT_INCLUDED",
      "pattern": "窓枠奥行き不足なのにふかし枠費用を見積もりに含めない",
      "severity": "⚠️ MEDIUM",
      "reason": "マンションや古い住宅は窓枠奥行きが50mm未満のケースが多い。ふかし枠（1箇所1〜3万円）が必要なのに見積もりに含めると後から追加請求になる",
      "対処": "着工前に全窓の窓枠奥行きを計測。ふかし枠が必要かどうかを見積もりに明示させる"
    },
    {
      "code": "GLASS_ONLY_OVERSELL",
      "pattern": "断熱目的なのにガラス交換のみを勧める",
      "severity": "⚠️ MEDIUM",
      "reason": "ガラス交換のみではサッシ・窓枠からの熱損失が残り、サッシに結露が発生する。断熱効果は内窓設置より大幅に劣る",
      "対処": "断熱・結露防止目的なら内窓設置を優先。ガラス交換は補助金要件も厳しい"
    },
    {
      "code": "MANSION_OUTER_WINDOW_PROPOSED",
      "pattern": "マンションで外窓交換を提案",
      "severity": "🔴 CRITICAL",
      "reason": "マンションの外窓は共用部のため区分所有者が単独で交換できないケースが多い。管理規約・管理組合の許可が必要",
      "対処": "マンションでは内窓設置が基本。外窓変更は管理組合の許可確認が必須"
    },
    {
      "code": "CONTRACT_BEFORE_RESERVATION",
      "pattern": "補助金申請予約（事前登録）なしで着工する",
      "severity": "🚨 HIGH",
      "reason": "先進的窓リノベ2026は原則として着工前の交付申請予約が必要。事後申請は認められない場合がある",
      "対処": "着工前に業者経由で交付申請予約を完了してから工事開始"
    }
  ],
  "negotiation_tips": [
    "複数窓を同時発注すると施工費が1箇所あたり安くなる（まとめ発注が鉄則）",
    "先進的窓リノベ2026は予算上限到達次第終了。補助金を使うなら早急に申請",
    "住宅省エネ支援事業者登録済みの業者かどうかを最初に確認",
    "SSグレード（最高断熱）は補助金が最大になるが材料費も高い。工事費引後のネットコストで比較する",
    "マンションは管理規約・管理組合への届出確認を先に済ませる",
    "窓枠の奥行き測定（50mm以上あれば標準施工）を契約前に確認",
    "先進的窓リノベとみらいエコ住宅2026の連携申請で断熱+バリアフリー等の追加工事も補助対象化できる",
    "防音目的の場合は防音合わせガラス対応の内窓を選ぶ（ラミシャット30・40等）",
    "工事は1日で完了（複数職人体制）のため、引越し直前・直後でも対応可能"
  ],
  "effects_and_roi": {
    "thermal_insulation": "窓からの熱損失は住宅全体の約50〜60%。内窓設置で冷暖房費を年間10〜20%削減効果",
    "condensation": "外気温と室温の差による結露をアルゴンガス入りLow-Eガラスで大幅抑制",
    "sound_insulation": "防音グレード選択で外部騒音を20〜30dB低減（幹線道路・線路沿いで効果大）",
    "crime_prevention": "窓が二重になり、こじ開けに時間がかかるため防犯効果あり",
    "payback_period": "補助金活用後のネット費用÷年間光熱費削減額。補助金フル活用なら5〜10年でペイが目安"
  },
  "trade_knowledge": {
    "summary": "内窓1箇所4〜20万円・施工30分〜1時間。先進的窓リノベ2026で最大100万円補助（予算上限先着順）。複数窓同時発注で単価低下。マンションは管理規約・外窓は共用部に注意。住宅省エネ支援事業者登録業者でないと補助金申請不可。2026年4月時点で申請進行中のため補助金を狙うなら早急に動く。",
    "best_strategy": "先進的窓リノベ2026の予算残量を公式サイトで確認→住宅省エネ支援事業者に問い合わせ→全室まとめて見積もり→補助金申請予約→着工",
    "window_reform_vs_this_file": "window_reform.jsonは外窓交換・サッシ交換全般をカバー。本ファイルは省エネ補助金と内窓設置に特化した独立データベース",
    "knowledge_source": "TOshi 30年大工・現場監督・CMR実務 / 環境省先進的窓リノベ2026公式データ / LIXIL・YKKap 2026年カタログ"
  },
  "customer_scenario_guide": [
    {
      "case": "冬の寒さ・結露が気になる（戸建て全室）",
      "recommendation": "全室内窓設置（10〜15箇所）・先進的窓リノベ2026フル活用",
      "cost_range": { "min": 600000, "max": 1500000 },
      "subsidy": "40〜80万円補助の可能性",
      "net_cost": { "min": 200000, "max": 900000 },
      "note": "補助金活用後のネットコストが最安になる最大プラン"
    },
    {
      "case": "道路・線路沿いで騒音が気になる（1〜2部屋）",
      "recommendation": "防音合わせガラス内窓（ラミシャット30/40対応）2〜4箇所",
      "cost_range": { "min": 120000, "max": 400000 },
      "subsidy": "5万円以上申請できれば補助対象",
      "note": "防音合わせガラスは普通の内窓より材料費高め。補助金の最低申請額5万円を確認"
    },
    {
      "case": "マンションの結露をなんとかしたい",
      "recommendation": "内窓設置（管理規約確認後）・Sグレード以上",
      "cost_range": { "min": 200000, "max": 450000 },
      "subsidy": "12〜29万円補助の可能性",
      "note": "マンションは外窓交換不可がほとんど。内窓設置が唯一の選択肢"
    },
    {
      "case": "寒い部屋だけ先に1〜2箇所試したい",
      "recommendation": "内窓1〜2箇所設置（様子見）",
      "cost_range": { "min": 60000, "max": 200000 },
      "note": "補助金は5万円以上の申請が必要。1箇所だけだと補助金申請できない場合あり"
    },
    {
      "case": "省エネリフォーム全体（断熱材＋内窓）",
      "recommendation": "みらいエコ住宅2026と先進的窓リノベの連携申請",
      "cost_range": { "min": 500000, "max": 3000000 },
      "note": "insulation_work.jsonと連携。最大200万円超の補助を組み合わせられる可能性あり"
    }
  ],
  "business_size_based_pricing": {
    "_description": "業者規模4区分別 妥当な利益率レンジ（2026年4月時点・内窓設置）",
    "4区分別_妥当な利益率レンジ": {
      "区分1_個人サッシ職人": {
        "代表例": "窓・サッシ専門の個人事業者",
        "粗利率レンジ": "25-35%",
        "HS基準からの係数": "0.85-0.92",
        "HS推奨度": "★★★☆☆",
        "特徴": "価格安い。補助金申請サポート力は業者次第。住宅省エネ支援事業者登録確認必須"
      },
      "区分2_中小窓専門店": {
        "代表例": "地域の窓・サッシ専門リフォーム店（住宅省エネ支援事業者登録済み）",
        "粗利率レンジ": "25-35%",
        "HS基準からの係数": "1.00-1.05",
        "HS推奨度": "★★★★★ **第一推奨**",
        "特徴": "補助金申請に慣れており手続きをスムーズにサポート。複数メーカーを扱い最適提案が可能"
      },
      "区分3_人気リフォーム会社": {
        "代表例": "LIXIL・YKK認定施工店・総合リフォーム会社の窓部門",
        "粗利率レンジ": "30-40%",
        "HS基準からの係数": "1.10-1.18",
        "HS推奨度": "★★★★☆",
        "特徴": "補助金サポート充実。メーカー保証あり。費用はやや高め"
      },
      "区分4_大手リフォーム_HM系": {
        "代表例": "大手ハウスメーカーのリフォーム部門",
        "粗利率レンジ": "40-50%",
        "HS基準からの係数": "1.30-1.45",
        "HS推奨度": "★★☆☆☆",
        "特徴": "価格が中小の1.3〜1.5倍。窓専門店の方が補助金申請も慣れていることが多い"
      }
    }
  },
  "cross_references": {
    "related_json_files": [
      "window_reform.json（外窓交換・サッシ交換全般）",
      "insulation_work.json（断熱材との組み合わせ・みらいエコ住宅連携）",
      "solar_battery_work.json（省エネリフォーム全体最適化）",
      "electrical_work.json（インターホン・センサー等と同時施工）",
      "gaiheki_tosou.json（外壁塗装と同時施工で足場共有）"
    ]
  },
  "iran_tariff_2026_impact": {
    "影響資材": [
      "アルミサッシ材料（外窓交換の場合）+10-20%",
      "樹脂サッシ（石油系原料）+5-10%",
      "複層ガラス（ガラス素材）+5-10%"
    ],
    "内窓への影響": "内窓本体（樹脂フレーム+複層ガラス）は5〜10%程度の値上がりリスク。補助金額は変わらないため、補助金効果が相対的に減少する前に早期申請が有利",
    "_impact_summary": "補助金のある今が最もコスパが良い。材料値上がり前・補助金予算終了前の早期実施を強く推奨"
  }
}
